CHANGES.rst
MANIFEST.in
README.rst
_groonga.c
setup.py
pyroonga/__init__.py
pyroonga/exceptions.py
pyroonga/groonga.py
pyroonga/utils.py
pyroonga.egg-info/PKG-INFO
pyroonga.egg-info/SOURCES.txt
pyroonga.egg-info/dependency_links.txt
pyroonga.egg-info/not-zip-safe
pyroonga.egg-info/top_level.txt
pyroonga/odm/__init__.py
pyroonga/odm/attributes.py
pyroonga/odm/query.py
pyroonga/odm/table.py
pyroonga/tests/__init__.py
pyroonga/tests/utils.py
pyroonga/tests/functional/__init__.py
pyroonga/tests/functional/conftest.py
pyroonga/tests/functional/test___init__.py
pyroonga/tests/functional/test_groonga.py
pyroonga/tests/functional/odm/__init__.py
pyroonga/tests/functional/odm/test_query.py
pyroonga/tests/functional/odm/test_table.py
pyroonga/tests/unit/__init__.py
pyroonga/tests/unit/test___init__.py
pyroonga/tests/unit/test_groonga.py
pyroonga/tests/unit/test_utils.py
pyroonga/tests/unit/odm/__init__.py
pyroonga/tests/unit/odm/test_attributes.py
pyroonga/tests/unit/odm/test_query.py
pyroonga/tests/unit/odm/test_table.py