Metadata-Version: 1.1
Name: pyroonga
Version: 0.5.2
Summary: Python interface for groonga
Home-page: https://github.com/naoina/pyroonga
Author: Naoya Inada
Author-email: naoina@kuune.org
License: MIT
Keywords: groonga fulltext search engine
Platform: UNKNOWN
Classifier: Development Status :: 3 - Alpha
Classifier: Intended Audience :: Developers
Classifier: License :: OSI Approved :: MIT License
Classifier: Programming Language :: Python
Classifier: Topic :: Internet :: WWW/HTTP :: Indexing/Search
Classifier: Topic :: Software Development :: Libraries
